{"__symbolic":"module","version":4,"metadata":{"HomeModule":{"__symbolic":"class","decorators":[{"__symbolic":"call","expression":{"__symbolic":"reference","module":"@angular/core","name":"NgModule","line":20,"character":1},"arguments":[{"imports":[{"__symbolic":"reference","module":"@angular/common","name":"CommonModule","line":22,"character":4},{"__symbolic":"reference","name":"ɵa"},{"__symbolic":"reference","module":"@angular/forms","name":"FormsModule","line":24,"character":4},{"__symbolic":"reference","module":"@angular/forms","name":"ReactiveFormsModule","line":25,"character":4},{"__symbolic":"reference","name":"ɵh"},{"__symbolic":"reference","name":"ɵi"},{"__symbolic":"reference","name":"ɵm"},{"__symbolic":"reference","module":"@angular/flex-layout","name":"FlexLayoutModule","line":29,"character":4},{"__symbolic":"reference","module":"ngxf-uploader","name":"NgxfUploaderModule","line":30,"character":4},{"__symbolic":"reference","module":"@hamastar/hm-carousel","name":"HmCarouselModule","line":31,"character":4}],"declarations":[{"__symbolic":"reference","name":"ɵb"},{"__symbolic":"reference","name":"ɵp"},{"__symbolic":"reference","name":"ɵq"},{"__symbolic":"reference","name":"ɵs"}],"providers":[{"__symbolic":"reference","module":"@hamastar/http","name":"HmDefaultHttpClient","line":40,"character":4},{"__symbolic":"reference","name":"ɵd"},{"__symbolic":"reference","name":"ɵt"},{"__symbolic":"reference","name":"ɵr"}]}]}],"members":{}},"ɵa":{"__symbolic":"class","decorators":[{"__symbolic":"call","expression":{"__symbolic":"reference","module":"@angular/core","name":"NgModule","line":15,"character":1},"arguments":[{"imports":[{"__symbolic":"call","expression":{"__symbolic":"select","expression":{"__symbolic":"reference","module":"@angular/router","name":"RouterModule","line":16,"character":12},"member":"forChild"},"arguments":[[{"path":"","component":{"__symbolic":"reference","name":"ɵb"},"resolve":{"data":{"__symbolic":"reference","name":"ɵe"}}}]]}],"exports":[{"__symbolic":"reference","module":"@angular/router","name":"RouterModule","line":17,"character":12}],"providers":[{"__symbolic":"reference","name":"ɵe"}]}]}],"members":{}},"ɵb":{"__symbolic":"class","extends":{"__symbolic":"reference","name":"ɵc"},"decorators":[{"__symbolic":"call","expression":{"__symbolic":"reference","module":"@angular/core","name":"Component","line":8,"character":1},"arguments":[{"selector":"app-home","template":"<div class=\"center\">\n  <app-post-item (addItem)=\"addItem($event)\" [userId]=\"userId\" [postId]=\"postId\"></app-post-item>\n  <app-wall-item (deleteAction)=\"deleteAction($event)\" *ngFor=\"let item of data.result\" [post]=\"item\"></app-wall-item>\n  <div class=\"text-c\" *ngIf=\"data.totalCount > data.result.length\">\n    <button mat-mini-fab color=\"accent\">\n      <mat-icon matTooltip=\"輸入\" (click)=\"loadMore()\">expand_more</mat-icon>\n    </button>\n  </div>\n</div>\n<app-navbar></app-navbar>\n","styles":[".center {\n  margin: 7% auto 0 auto;\n  width: 667px; }\n\n@media screen and (max-width: 1280px) {\n  .center {\n    margin: 10% auto 0 auto; } }\n\n@media screen and (max-width: 768px) {\n  .center {\n    margin: 15% auto 0 auto;\n    width: 100%; } }\n\n@media screen and (max-width: 666px) {\n  .center {\n    margin: 30% auto 0 auto;\n    width: 100%; } }\n"]}]}],"members":{"userId":[{"__symbolic":"property","decorators":[{"__symbolic":"call","expression":{"__symbolic":"reference","module":"@angular/core","name":"Input","line":43,"character":3}}]}],"postId":[{"__symbolic":"property","decorators":[{"__symbolic":"call","expression":{"__symbolic":"reference","module":"@angular/core","name":"Input","line":44,"character":3}}]}],"__ctor__":[{"__symbolic":"constructor","parameters":[{"__symbolic":"reference","module":"@angular/router","name":"ActivatedRoute","line":47,"character":20},{"__symbolic":"reference","name":"ɵd"}]}],"ngOnInit":[{"__symbolic":"method"}],"addItem":[{"__symbolic":"method"}],"deleteAction":[{"__symbolic":"method"}],"loadMore":[{"__symbolic":"method"}]}},"ɵc":{"__symbolic":"class","members":{"ngOnDestroy":[{"__symbolic":"method"}]}},"ɵd":{"__symbolic":"class","decorators":[{"__symbolic":"call","expression":{"__symbolic":"reference","module":"@angular/core","name":"Injectable","line":5,"character":1}}],"members":{"__ctor__":[{"__symbolic":"constructor","parameters":[{"__symbolic":"reference","name":"ɵf"}]}],"get":[{"__symbolic":"method"}]}},"ɵe":{"__symbolic":"class","decorators":[{"__symbolic":"call","expression":{"__symbolic":"reference","module":"@angular/core","name":"Injectable","line":14,"character":1}}],"members":{"__ctor__":[{"__symbolic":"constructor","parameters":[{"__symbolic":"reference","name":"ɵd"}]}],"resolve":[{"__symbolic":"method"}]}},"ɵf":{"__symbolic":"class","decorators":[{"__symbolic":"call","expression":{"__symbolic":"reference","module":"@angular/core","name":"Injectable","line":11,"character":1}}],"members":{"__ctor__":[{"__symbolic":"constructor","parameters":[{"__symbolic":"reference","module":"@hamastar/http","name":"HmDefaultHttpClient","line":14,"character":34},{"__symbolic":"reference","module":"ngxf-uploader","name":"NgxfUploaderService","line":15,"character":21},{"__symbolic":"reference","module":"@hamastar/block-view","name":"BlockViewService","line":16,"character":31}]}],"get":[{"__symbolic":"method"}],"delete":[{"__symbolic":"method"}],"createFunction":[{"__symbolic":"method"}]}},"ɵg":{"parse":{"dateInput":"YYYY/MM/DD"},"display":{"dateInput":"YYYY/MM/DD","monthYearLabel":"YYYY MMM","dateA11yLabel":"YYYY/MM/DD","monthYearA11yLabel":"YYYY MMM"}},"ɵh":{"__symbolic":"class","decorators":[{"__symbolic":"call","expression":{"__symbolic":"reference","module":"@angular/core","name":"NgModule","line":47,"character":1},"arguments":[{"exports":[{"__symbolic":"reference","module":"@angular/material","name":"MatButtonModule","line":49,"character":4},{"__symbolic":"reference","module":"@angular/material","name":"MatIconModule","line":50,"character":4},{"__symbolic":"reference","module":"@angular/material","name":"MatButtonModule","line":51,"character":4},{"__symbolic":"reference","module":"@angular/material","name":"MatButtonToggleModule","line":52,"character":4},{"__symbolic":"reference","module":"@angular/material","name":"MatRippleModule","line":53,"character":4},{"__symbolic":"reference","module":"@angular/material","name":"MatSidenavModule","line":54,"character":4},{"__symbolic":"reference","module":"@angular/material","name":"MatToolbarModule","line":55,"character":4},{"__symbolic":"reference","module":"@angular/material","name":"MatListModule","line":56,"character":4},{"__symbolic":"reference","module":"@angular/material","name":"MatMenuModule","line":57,"character":4},{"__symbolic":"reference","module":"@angular/material","name":"MatStepperModule","line":58,"character":4},{"__symbolic":"reference","module":"@angular/material","name":"MatFormFieldModule","line":59,"character":4},{"__symbolic":"reference","module":"@angular/material","name":"MatInputModule","line":60,"character":4},{"__symbolic":"reference","module":"@angular/material","name":"MatAutocompleteModule","line":61,"character":4},{"__symbolic":"reference","module":"@angular/material","name":"MatDatepickerModule","line":62,"character":4},{"__symbolic":"reference","module":"@angular/material-moment-adapter","name":"MatMomentDateModule","line":63,"character":4},{"__symbolic":"reference","module":"@angular/material","name":"MatSelectModule","line":64,"character":4},{"__symbolic":"reference","module":"@angular/material","name":"MatCheckboxModule","line":65,"character":4},{"__symbolic":"reference","module":"@angular/material","name":"MatRadioModule","line":66,"character":4},{"__symbolic":"reference","module":"@angular/material","name":"MatSlideToggleModule","line":67,"character":4},{"__symbolic":"reference","module":"@angular/material","name":"MatSliderModule","line":68,"character":4},{"__symbolic":"reference","module":"@angular/material","name":"MatGridListModule","line":69,"character":4},{"__symbolic":"reference","module":"@angular/material","name":"MatCardModule","line":70,"character":4},{"__symbolic":"reference","module":"@angular/material","name":"MatProgressBarModule","line":71,"character":4},{"__symbolic":"reference","module":"@angular/material","name":"MatProgressSpinnerModule","line":72,"character":4},{"__symbolic":"reference","module":"@angular/material","name":"MatDialogModule","line":73,"character":4},{"__symbolic":"reference","module":"@angular/material","name":"MatChipsModule","line":74,"character":4},{"__symbolic":"reference","module":"@angular/material","name":"MatTooltipModule","line":75,"character":4},{"__symbolic":"reference","module":"@angular/material","name":"MatSnackBarModule","line":76,"character":4}],"providers":[{"provide":{"__symbolic":"reference","module":"@angular/material","name":"MAT_DATE_LOCALE","line":79,"character":15},"useValue":"zh-TW"},{"provide":{"__symbolic":"reference","module":"@angular/material","name":"MAT_DATE_FORMATS","line":80,"character":15},"useValue":{"__symbolic":"reference","name":"ɵg"}}]}]}],"members":{}},"ɵi":{"__symbolic":"class","decorators":[{"__symbolic":"call","expression":{"__symbolic":"reference","module":"@angular/core","name":"NgModule","line":27,"character":1},"arguments":[{"imports":[{"__symbolic":"reference","module":"@angular/common","name":"CommonModule","line":29,"character":4}],"declarations":[[{"__symbolic":"reference","name":"ɵj"}],[{"__symbolic":"reference","name":"ɵk"}]],"exports":[[{"__symbolic":"reference","name":"ɵj"}],[{"__symbolic":"reference","name":"ɵk"}]]}]}],"members":{},"statics":{"forRoot":{"__symbolic":"function","parameters":[],"value":{"ngModule":{"__symbolic":"reference","name":"ɵi"},"providers":[{"__symbolic":"reference","name":"ɵl"}]}}}},"ɵm":{"__symbolic":"class","decorators":[{"__symbolic":"call","expression":{"__symbolic":"reference","module":"@angular/core","name":"NgModule","line":24,"character":1},"arguments":[{"imports":[{"__symbolic":"reference","module":"@angular/common","name":"CommonModule","line":26,"character":4},{"__symbolic":"reference","module":"@hamastar/block-view","name":"BlockViewModule","line":27,"character":4}],"declarations":[[{"__symbolic":"reference","name":"ɵn"}]],"exports":[[{"__symbolic":"reference","name":"ɵn"}]]}]}],"members":{},"statics":{"forRoot":{"__symbolic":"function","parameters":[],"value":{"ngModule":{"__symbolic":"reference","name":"ɵm"},"providers":[[{"__symbolic":"reference","name":"ɵo"}]]}}}},"ɵp":{"__symbolic":"class","decorators":[{"__symbolic":"call","expression":{"__symbolic":"reference","module":"@angular/core","name":"Component","line":2,"character":1},"arguments":[{"selector":"app-navbar","template":"<nav class=\"navbar\" fxLayoutAlign=\"center center\" [appFixedMenu]=\"'fixed'\" [howFixed]=\"'top'\">\n  <div class=\"block\" fxLayoutAlign=\"space-between center\">\n    <a class=\"logo\" fxLayoutAlign=\"center center\">\n      <mat-icon class=\"interval\">forum</mat-icon>\n      <span class=\"text\">HamaWall</span>\n    </a>\n    <div fxLayoutAlign=\"space-around center\" class=\"search\">\n      <mat-icon>search</mat-icon>\n      <input type=\"text\" class=\"text\" placeholder=\"搜尋\">\n    </div>\n    <div class=\"menu-icon\" fxLayout fxLayoutGap=\"1em\">\n      <mat-icon class=\"cursor-pointer\">favorite_border</mat-icon>\n      <mat-icon class=\"cursor-pointer\">account_circle</mat-icon>\n    </div>\n  </div>\n</nav>\n","styles":[".navbar {\n  position: fixed;\n  top: 0;\n  width: 100%;\n  height: 5em;\n  border-bottom: 1px solid rgba(0, 0, 0, 0.0975);\n  -webkit-transition: 0.3s cubic-bezier(0.45, 0.8, 0.45, 1);\n  transition: 0.3s cubic-bezier(0.45, 0.8, 0.45, 1); }\n  .navbar .block {\n    width: 70%; }\n    .navbar .block .logo {\n      font-size: 2em; }\n      .navbar .block .logo .interval {\n        border-right: 1px solid rgba(0, 0, 0, 0.4);\n        padding-right: 1em;\n        -webkit-transition: 0.3s cubic-bezier(0.45, 0.8, 0.45, 1);\n        transition: 0.3s cubic-bezier(0.45, 0.8, 0.45, 1); }\n      .navbar .block .logo .text {\n        padding-left: 1em;\n        font-family: monospace; }\n    .navbar .block .search {\n      border: 1px solid rgba(0, 0, 0, 0.0975); }\n      .navbar .block .search .text {\n        background: transparent;\n        border: 0;\n        outline: 0;\n        text-align: center; }\n  .navbar.fixed {\n    -webkit-box-shadow: 0 3px 5px -1px rgba(0, 0, 0, 0.2), 0 6px 10px 0 rgba(0, 0, 0, 0.14), 0 1px 18px 0 rgba(0, 0, 0, 0.12);\n            box-shadow: 0 3px 5px -1px rgba(0, 0, 0, 0.2), 0 6px 10px 0 rgba(0, 0, 0, 0.14), 0 1px 18px 0 rgba(0, 0, 0, 0.12);\n    height: 3em;\n    background: white; }\n    .navbar.fixed .block .logo {\n      font-size: 2em; }\n      .navbar.fixed .block .logo .interval {\n        border: 0;\n        padding: 0; }\n      .navbar.fixed .block .logo .text {\n        display: none; }\n\n@media screen and (max-width: 667px) {\n  .navbar .block .logo {\n    font-size: 1.5em; }\n  .navbar .block .search {\n    display: none !important; } }\n"]}]}],"members":{"__ctor__":[{"__symbolic":"constructor"}],"ngOnInit":[{"__symbolic":"method"}]}},"ɵq":{"__symbolic":"class","extends":{"__symbolic":"reference","name":"ɵc"},"decorators":[{"__symbolic":"call","expression":{"__symbolic":"reference","module":"@angular/core","name":"Component","line":17,"character":1},"arguments":[{"selector":"app-wall-item","template":"<mat-card class=\"card\">\n  <mat-card-header>\n    <mat-card-title>{{ post.userId }}</mat-card-title>\n    <mat-card-subtitle>{{ post.time | date:'yyyy/MM/dd' }}</mat-card-subtitle>\n    <img mat-card-avatar src=\"assets/images/evan.jpg\" />\n    <button mat-icon-button class=\"card-action\" [matMenuTriggerFor]=\"menu\">\n      <mat-icon>more_vert</mat-icon>\n    </button>\n    <mat-menu #menu=\"matMenu\">\n      <button mat-menu-item (click)=\"deleteItem()\">刪除</button>\n    </mat-menu>\n  </mat-card-header>\n\n  <img *ngIf=\"post.files.length === 1\" mat-card-image [src]=\"'http://localhost:50696/' + post.files[0].url\"/>\n\n  <carousel-container *ngIf=\"post.files.length > 1\">\n\n    <section carousel-items-container class=\"pane-container\">\n\n      <article class=\"pane\" *ngFor=\"let avatar of post.files; let i = index;\"\n      carousel-item\n      #articleList\n      [style.backgroundImage]=\"('http://localhost:50696/' + avatar.url) | safe:'background-image'\"\n      >\n      </article>\n\n      <!-- <img carousel-item class=\"magin-size\" mat-card-image *ngFor=\"let item of post.files\" [src]=\"'http://localhost:50696/' + item.url\"\n      /> -->\n\n    </section>\n\n    <ng-template #carouselPrev>\n      <mat-icon class=\"icon\">keyboard_arrow_left</mat-icon>\n    </ng-template>\n\n    <ng-template #carouselNext>\n      <mat-icon class=\"icon\">keyboard_arrow_right</mat-icon>\n    </ng-template>\n\n    <ng-template #carouselDot let-model>\n      <div class=\"ball\" [class.visible]=\"model.index === model.currentIndex\"></div>\n    </ng-template>\n\n  </carousel-container>\n\n  <div>\n    <mat-icon class=\"cursor-pointer  magin-right1em\">favorite_border</mat-icon>\n    <mat-icon class=\"cursor-pointer\">chat_bubble_outline</mat-icon>\n  </div>\n  <mat-card-content class=\"content\">\n    <p class=\"reply\">\n      <strong>{{ post.userId }}：</strong>\n      <span>{{ post.content }}</span>\n    </p>\n    <p class=\"reply\" *ngFor=\"let item of post.reply\">\n      <strong>{{ item.userId }}：</strong>\n      <span>{{ item.content }}</span>\n    </p>\n    <p class=\"load-more\">{{ post.time | agoTime }}</p>\n    <!-- <p class=\"load-more\">載入更多留言</p> -->\n  </mat-card-content>\n\n  <mat-card-footer class=\"footer\" fxLayoutAlign=\"center\">\n    <textarea class=\"reply-input\" placeholder=\"留言........\" [(ngModel)]=\"textContent\"></textarea>\n    <button mat-icon-button color=\"primary\" (click)=\"reply()\">\n      <mat-icon>send</mat-icon>\n    </button>\n  </mat-card-footer>\n</mat-card>\n","styles":[".card {\n  margin-bottom: 2em; }\n  .card .card-action {\n    position: absolute;\n    right: 0;\n    margin-right: 2em; }\n  .card .magin-right1em {\n    margin-right: 1em; }\n  .card .load-more {\n    cursor: pointer;\n    color: #999; }\n  .card .content p {\n    margin-bottom: .5em; }\n  .card .footer {\n    padding-bottom: .2em; }\n    .card .footer .reply-input {\n      width: 85%;\n      border: none;\n      outline: none;\n      max-width: 90%;\n      resize: none;\n      height: 3em; }\n\n.ball {\n  width: 15px;\n  height: 15px;\n  border-radius: 100%;\n  background: #efefef; }\n  .ball.visible {\n    background: #3d7df7; }\n\n.pane-container {\n  height: 100%;\n  width: 100%;\n  margin: 0;\n  padding: 0;\n  position: relative;\n  line-height: 0; }\n  .pane-container .magin-size {\n    margin: 0 0 16px 0; }\n  .pane-container .pane {\n    display: -webkit-inline-box;\n    display: -ms-inline-flexbox;\n    display: inline-flex;\n    -webkit-box-pack: center;\n        -ms-flex-pack: center;\n            justify-content: center;\n    width: 100%;\n    background-attachment: scroll;\n    background-size: 100% 100%;\n    background-position: center; }\n\n.pane-container.transition {\n  -webkit-transition: left .4s ease-in-out;\n  transition: left .4s ease-in-out; }\n\n.icon {\n  font-size: 3em;\n  color: #cccccc;\n  padding-right: 1rem;\n  cursor: pointer; }\n\n@media (max-width: 600px) {\n  .pane {\n    width: calc(100% + 32px);\n    margin: 16px 0; } }\n"]}]}],"members":{"post":[{"__symbolic":"property","decorators":[{"__symbolic":"call","expression":{"__symbolic":"reference","module":"@angular/core","name":"Input","line":160,"character":3}}]}],"deleteAction":[{"__symbolic":"property","decorators":[{"__symbolic":"call","expression":{"__symbolic":"reference","module":"@angular/core","name":"Output","line":163,"character":3}}]}],"articleList":[{"__symbolic":"property","decorators":[{"__symbolic":"call","expression":{"__symbolic":"reference","module":"@angular/core","name":"ViewChildren","line":167,"character":3},"arguments":["articleList"]}]}],"__ctor__":[{"__symbolic":"constructor","parameters":[{"__symbolic":"reference","name":"ɵr"}]}],"ngOnInit":[{"__symbolic":"method"}],"ngAfterViewInit":[{"__symbolic":"method"}],"onResize":[{"__symbolic":"method","decorators":[{"__symbolic":"call","expression":{"__symbolic":"reference","module":"@angular/core","name":"HostListener","line":179,"character":3},"arguments":["window:resize",["$event"]]}]}],"deleteItem":[{"__symbolic":"method"}],"reply":[{"__symbolic":"method"}],"getHeight":[{"__symbolic":"method"}]}},"ɵr":{"__symbolic":"class","decorators":[{"__symbolic":"call","expression":{"__symbolic":"reference","module":"@angular/core","name":"Injectable","line":5,"character":1}}],"members":{"__ctor__":[{"__symbolic":"constructor","parameters":[{"__symbolic":"reference","name":"ɵf"}]}],"deleteItem":[{"__symbolic":"method"}],"replyItem":[{"__symbolic":"method"}]}},"ɵs":{"__symbolic":"class","extends":{"__symbolic":"reference","module":"@hamastar/auto-destroy","name":"AutoDestroy","line":79,"character":39},"decorators":[{"__symbolic":"call","expression":{"__symbolic":"reference","module":"@angular/core","name":"Component","line":8,"character":1},"arguments":[{"selector":"app-post-item","template":"<div class=\"post-item\">\n  <header class=\"header\" fxLayoutAlign=\"space-around center\">\n    <section fxLayout=\"column\" fxLayoutAlign=\"center\">\n      <h3>\n        分享你的生活吧\n      </h3>\n      <p>{{ today | date:'yyyy/MM/dd' }}</p>\n    </section>\n    <img class=\"avatar\" src=\"assets/images/evan.jpg\" alt=\"\">\n  </header>\n  <section class=\"content\" fxLayoutAlign=\"center\">\n    <textarea class=\"reply-input\" placeholder=\"kevinwang6303，你在想些什麼呢!\" [(ngModel)]=\"textContent\"></textarea>\n  </section>\n  <section class=\"content-img\">\n    <img [ngClass]=\"{'active':item.choice}\" (click)=\"choiceItem(item)\" class=\"img\" [src]=\"item.blob | safe:'resourceUrl'\" alt=\"\"\n      *ngFor=\"let item of filesArray\">\n  </section>\n  <footer fxLayoutAlign=\"space-between\">\n    <div>\n      <button mat-raised-button color=\"accent\" (click)=\"tempFiles.click()\">\n        <input #tempFiles type=\"file\" class=\"none\" (ngxf-select)=\"uploadFile($event)\" accept=\"image/*,.svg\" multiple/> 上傳圖片\n      </button>\n      <button mat-raised-button color=\"warn\" (click)=\"remove()\">刪除選擇</button>\n    </div>\n    <button mat-raised-button color=\"primary\" (click)=\"shared()\">分享\n    </button>\n  </footer>\n</div>\n","styles":[".post-item {\n  -webkit-box-shadow: 0 3px 1px -2px rgba(0, 0, 0, 0.2), 0 2px 2px 0 rgba(0, 0, 0, 0.14), 0 1px 5px 0 rgba(0, 0, 0, 0.12);\n          box-shadow: 0 3px 1px -2px rgba(0, 0, 0, 0.2), 0 2px 2px 0 rgba(0, 0, 0, 0.14), 0 1px 5px 0 rgba(0, 0, 0, 0.12);\n  background: white;\n  margin-bottom: 2em; }\n  .post-item .avatar {\n    width: 80px;\n    height: 80px;\n    border-radius: 50%; }\n  .post-item .content {\n    border-bottom: 1px solid rgba(0, 0, 0, 0.08);\n    padding-bottom: 0.3em; }\n    .post-item .content .reply-input {\n      width: 90%;\n      border: 1px solid rgba(0, 0, 0, 0.08);\n      outline: none;\n      max-width: 90%;\n      resize: none;\n      height: 4em; }\n  .post-item .content-img {\n    border-bottom: 1px solid rgba(0, 0, 0, 0.08); }\n    .post-item .content-img .img {\n      opacity: .5;\n      margin: .3em;\n      width: 100px;\n      height: 100px;\n      cursor: pointer; }\n      .post-item .content-img .img:hover {\n        opacity: 1; }\n      .post-item .content-img .img.active {\n        border: 2px solid red;\n        -webkit-box-sizing: border-box;\n                box-sizing: border-box;\n        opacity: 1; }\n\n@media screen and (max-width: 666px) {\n  .post-item .content-img .img {\n    margin: .7em; } }\n"]}]}],"members":{"postId":[{"__symbolic":"property","decorators":[{"__symbolic":"call","expression":{"__symbolic":"reference","module":"@angular/core","name":"Input","line":89,"character":3}}]}],"userId":[{"__symbolic":"property","decorators":[{"__symbolic":"call","expression":{"__symbolic":"reference","module":"@angular/core","name":"Input","line":91,"character":3}}]}],"addItem":[{"__symbolic":"property","decorators":[{"__symbolic":"call","expression":{"__symbolic":"reference","module":"@angular/core","name":"Output","line":93,"character":3}}]}],"__ctor__":[{"__symbolic":"constructor","parameters":[{"__symbolic":"reference","name":"ɵt"},{"__symbolic":"reference","module":"@hamastar/block-view","name":"BlockViewService","line":97,"character":31}]}],"ngOnInit":[{"__symbolic":"method"}],"choiceItem":[{"__symbolic":"method"}],"uploadFile":[{"__symbolic":"method"}],"remove":[{"__symbolic":"method"}],"shared":[{"__symbolic":"method"}]}},"ɵt":{"__symbolic":"class","decorators":[{"__symbolic":"call","expression":{"__symbolic":"reference","module":"@angular/core","name":"Injectable","line":17,"character":1}}],"members":{"__ctor__":[{"__symbolic":"constructor","parameters":[{"__symbolic":"reference","name":"ɵf"}]}],"uploadFunction":[{"__symbolic":"method"}],"removeFunction":[{"__symbolic":"method"}],"uplaodFiles":[{"__symbolic":"method"}]}}},"origins":{"HomeModule":"./home.module","ɵa":"./home-routing.module","ɵb":"./home.component","ɵc":"./shared/base/auto.destroy","ɵd":"./home.service","ɵe":"./home.service","ɵf":"./theme/db-service/db-post.service","ɵg":"./shared-material/shared-material.module","ɵh":"./shared-material/shared-material.module","ɵi":"./shared/shared.module","ɵj":"./shared/directive","ɵk":"./shared/pipes","ɵl":"./shared/service","ɵm":"./theme/theme.module","ɵn":"./theme/pipes","ɵo":"./theme/db-service","ɵp":"./navbar/navbar.component","ɵq":"./wall-item/wall-item.component","ɵr":"./wall-item/wall-item.service","ɵs":"./post-item/post-item.component","ɵt":"./post-item/post-item.service"},"importAs":"hama-wall"}